{
  "project_info": {
    "project_number": "477546719510",
    "project_id": "holbegram-2506",
    "storage_bucket": "holbegram-2506.firebasestorage.app"
  },
  "client": [
    {
      "client_info": {
        "mobilesdk_app_id": "1:477546719510:android:80e33c4fd66d2bf1ea8837",
        "android_client_info": {
          "package_name": "com.arwenn.holbegram"
        }
      },
      "oauth_client": [],
      "api_key": [
        {
          "current_key": "AIzaSyC2MQvvKIXgSA409Z1KiIsyCdR3LCfjxr0"
        }
      ],
      "services": {
        "appinvite_service": {
          "other_platform_oauth_client": []
        }
      }
    }
  ],
  "configuration_version": "1"
}